{
    "@cr_type": "String", 
    "@timestamp": "String", 
    "@version": "String", 
    "action": "String", 
    "bitdef_time": "Double", 
    "count": "Long", 
    "geoip": "MAP", 
    "header_recipients": "String", 
    "host": "String", 
    "logtimestamp": "String", 
    "mail_source_ip": "String", 
    "message": "String", 
    "message-id": "String", 
    "offset": "Long", 
    "rbl": "MAP", 
    "receiver": "String", 
    "recipient": "String", 
    "rule_description": "String", 
    "rule_id": "Long", 
    "score": "Long", 
    "sender": "String", 
    "sender_domain": "String", 
    "sgn": "MAP", 
    "source": "String", 
    "src_ip": "String", 
    "subject": "String", 
    "tags": "array", 
    "type": "String", 
    "url": "MAP", 
    "user": "String"
}
